sgtpy/__init__.py
sgtpy/coloc_cy.cpython-39-darwin.so
sgtpy/config_asso.py
sgtpy/constants.py
sgtpy/database.py
sgtpy/math.py
sgtpy/mixture.py
sgtpy/saft.py
sgtpy/saft_forcefield.py
sgtpy/secondorder.py
sgtpy/database/saftgamma_database.xlsx
sgtpy/database/saftgamma_database_v018.xlsx
sgtpy/equilibrium/__init__.py
sgtpy/equilibrium/bubble.py
sgtpy/equilibrium/dew.py
sgtpy/equilibrium/equilibriumresult.py
sgtpy/equilibrium/flash.py
sgtpy/equilibrium/hazb.py
sgtpy/equilibrium/hazt.py
sgtpy/equilibrium/lle.py
sgtpy/equilibrium/multiflash.py
sgtpy/equilibrium/stability.py
sgtpy/fit/__init__.py
sgtpy/fit/fit_beta.py
sgtpy/fit/fit_cii.py
sgtpy/fit/fitbinary.py
sgtpy/fit/fitmulticomponent.py
sgtpy/gammamie_mixtures/B_monomer.py
sgtpy/gammamie_mixtures/__init__.py
sgtpy/gammamie_mixtures/a1_monomer.py
sgtpy/gammamie_mixtures/a1sB_monomer.py
sgtpy/gammamie_mixtures/a1s_monomer.py
sgtpy/gammamie_mixtures/a2_monomer.py
sgtpy/gammamie_mixtures/a2new_chain.py
sgtpy/gammamie_mixtures/a3_monomer.py
sgtpy/gammamie_mixtures/ahs_monomer.py
sgtpy/gammamie_mixtures/ares.py
sgtpy/gammamie_mixtures/association_aux.py
sgtpy/gammamie_mixtures/density_solver.py
sgtpy/gammamie_mixtures/g1sigma_chain.py
sgtpy/gammamie_mixtures/g2mca_chain.py
sgtpy/gammamie_mixtures/gammac_chain.py
sgtpy/gammamie_mixtures/gdHS_chain.py
sgtpy/gammamie_mixtures/ideal.py
sgtpy/gammamie_mixtures/lngmie_chain.py
sgtpy/gammamie_mixtures/monomer_aux.py
sgtpy/gammamie_mixtures/saftgammamie_mixture.py
sgtpy/gammamie_pure/B_monomer.py
sgtpy/gammamie_pure/EquilibriumResult.py
sgtpy/gammamie_pure/__init__.py
sgtpy/gammamie_pure/a1_monomer.py
sgtpy/gammamie_pure/a1sB_monomer.py
sgtpy/gammamie_pure/a1s_monomer.py
sgtpy/gammamie_pure/a2_monomer.py
sgtpy/gammamie_pure/a2new_chain.py
sgtpy/gammamie_pure/a3_monomer.py
sgtpy/gammamie_pure/ahs_monomer.py
sgtpy/gammamie_pure/ares.py
sgtpy/gammamie_pure/association_aux.py
sgtpy/gammamie_pure/critical_pure.py
sgtpy/gammamie_pure/density_solver.py
sgtpy-0.0.22.dist-info/LICENSE.txt
sgtpy-0.0.22.dist-info/METADATA
sgtpy-0.0.22.dist-info/WHEEL
sgtpy-0.0.22.dist-info/top_level.txt
sgtpy-0.0.22.dist-info/RECORD
