Metadata-Version: 2.1
Name: sgtpy
Version: 0.0.22
Summary: SAFT-VR-MIE EOS and SGT
Home-page: https://github.com/gustavochm/sgtpy
Author: Gustavo Chaparro Maldonado, Andres Mejia Matallana, Erich A. Muller
Author-email: g.chaparro-maldonado21@imperial.ac.uk
License: MIT
Download-URL: https://github.com/gustavochm/sgtpy.git
Keywords: SAFT-VR-Mie,SGT
Platform: Windows
Platform: Linux
Platform: Mac OS
Platform: Unix
License-File: LICENSE.txt
Requires-Dist: numpy
Requires-Dist: scipy
Requires-Dist: cython
Requires-Dist: numba
Requires-Dist: pandas
Requires-Dist: openpyxl
